juno_mutekey/__init__.py
juno_mutekey/api.py
juno_mutekey/middleware.py
juno_mutekey/response.py
juno_mutekey-0.0.3.dist-info/METADATA
juno_mutekey-0.0.3.dist-info/WHEEL
juno_mutekey-0.0.3.dist-info/top_level.txt
juno_mutekey-0.0.3.dist-info/RECORD
