Metadata-Version: 2.1
Name: juno-mutekey
Version: 0.0.3
Summary: Juno Python Web Framework built for learning purposes.
Home-page: UNKNOWN
Author: Kirill Ushkov
Author-email: kirillushkov2010@gmail.com
License: MIT
Platform: UNKNOWN
Classifier: Programming Language :: Python :: 3.6
Requires-Python: >=3.6.0
Requires-Dist: Jinja2 (==2.10.3)
Requires-Dist: parse (==1.19.0)
Requires-Dist: requests (==2.28.1)
Requires-Dist: requests-wsgi-adapter (==0.4.1)
Requires-Dist: WebOb (==1.8.7)
Requires-Dist: whitenoise (==6.2.0)
